{
  "project_info": {
    "project_number": "711812762807",
    "firebase_url": "https://organizeteam-ac243.firebaseio.com",
    "project_id": "organizeteam-ac243",
    "storage_bucket": "organizeteam-ac243.appspot.com"
  },
  "client": [
    {
      "client_info": {
        "mobilesdk_app_id": "1:711812762807:android:5cc8a9d86e9ec020505132",
        "android_client_info": {
          "package_name": "com.myapp.organizeteam"
        }
      },
      "oauth_client": [
        {
          "client_id": "711812762807-qb7rhf3fbt9spktmka2bhgkv77phi0ak.apps.googleusercontent.com",
          "client_type": 1,
          "android_info": {
            "package_name": "com.myapp.organizeteam",
            "certificate_hash": "9176b9abc23e003f7b8e1a039cc40108bb9589a9"
          }
        },
        {
          "client_id": "711812762807-50e9dg75v84js4u1pek2fcgt2vk88hfa.apps.googleusercontent.com",
          "client_type": 3
        }
      ],
      "api_key": [
        {
          "current_key": "AIzaSyBRtdi80SWUGCM7i08TCFB_C0ro3gg3X_8"
        }
      ],
      "services": {
        "appinvite_service": {
          "other_platform_oauth_client": [
            {
              "client_id": "711812762807-50e9dg75v84js4u1pek2fcgt2vk88hfa.apps.googleusercontent.com",
              "client_type": 3
            }
          ]
        }
      }
    }
  ],
  "configuration_version": "1"
}